origami/__init__.py
origami/cli.py
origami/clients/__init__.py
origami/clients/api.py
origami/clients/cache.py
origami/clients/rtu.py
origami/log_utils.py
origami/models/__init__.py
origami/models/api/__init__.py
origami/models/api/base.py
origami/models/api/datasources.py
origami/models/api/files.py
origami/models/api/outputs.py
origami/models/api/projects.py
origami/models/api/spaces.py
origami/models/api/users.py
origami/models/deltas/__init__.py
origami/models/deltas/base.py
origami/models/deltas/delta_types/__init__.py
origami/models/deltas/delta_types/cell_contents.py
origami/models/deltas/delta_types/cell_execute.py
origami/models/deltas/delta_types/cell_metadata.py
origami/models/deltas/delta_types/cell_output_collection.py
origami/models/deltas/delta_types/nb_cells.py
origami/models/deltas/delta_types/nb_metadata.py
origami/models/deltas/discriminators.py
origami/models/kernels.py
origami/models/notebook.py
origami/models/rtu/__init__.py
origami/models/rtu/base.py
origami/models/rtu/channels/__init__.py
origami/models/rtu/channels/files.py
origami/models/rtu/channels/kernels.py
origami/models/rtu/channels/system.py
origami/models/rtu/discriminators.py
origami/models/rtu/errors.py
origami/notebook/__init__.py
origami/notebook/builder.py
noteable_origami-2.0.0.dist-info/LICENSE
noteable_origami-2.0.0.dist-info/METADATA
noteable_origami-2.0.0.dist-info/WHEEL
noteable_origami-2.0.0.dist-info/entry_points.txt
noteable_origami-2.0.0.dist-info/RECORD
