Metadata-Version: 2.1
Name: noteable-origami
Version: 2.0.0
Summary: The Noteable API interface
Home-page: https://github.com/noteable-io/origami
License: BSD-3-Clause
Keywords: notebook,api,noteable
Author: Matt Seal
Author-email: matt@noteable.io
Maintainer: Matt Seal
Maintainer-email: matt@noteable.io
Requires-Python: >=3.8,<4.0
Classifier: Intended Audience :: Developers
Classifier: License :: OSI Approved :: BSD License
Classifier: Programming Language :: Python
Classifier: Programming Language :: Python :: 3
Classifier: Programming Language :: Python :: 3.8
Classifier: Programming Language :: Python :: 3.9
Classifier: Programming Language :: Python :: 3.10
Classifier: Programming Language :: Python :: 3.11
Classifier: Programming Language :: Python :: 3.12
Provides-Extra: cli
Requires-Dist: backoff (>=2.1.2,<3.0.0)
Requires-Dist: bitmath (>=1.3.3,<2.0.0)
Requires-Dist: cryptography (>=40.0)
Requires-Dist: diff-match-patch (>=20200713,<20200714)
Requires-Dist: httpx (>=0.22)
Requires-Dist: importlib-metadata (>=6.8.0)
Requires-Dist: jwt (>=1.3.1,<2.0.0)
Requires-Dist: nbformat (>=5.4.0,<6.0.0)
Requires-Dist: orjson (>=3.8.7,<4.0.0)
Requires-Dist: pydantic (>=2.4.2,<3.0.0)
Requires-Dist: sending (>=0.3.0,<0.4.0)
Requires-Dist: structlog ; extra == "cli"
Requires-Dist: typer (>=0.9.0,<0.10.0) ; extra == "cli"
Requires-Dist: websockets (>=11.0)
Project-URL: Repository, https://github.com/noteable-io/origami
